LICENSE
MANIFEST.in
Makefile
README.md
getting_started.ipynb
setup.py
test_kernel.py
godel-jupyter/__init__.py
godel-jupyter/__main__.py
godel-jupyter/kernel.json
godel-jupyter/kernel.py
godel-jupyter/magics/__init__.py
godel-jupyter/magics/db_magic.py
godel-jupyter/magics/save_to_magic.py
godel_jupyter.egg-info/PKG-INFO
godel_jupyter.egg-info/SOURCES.txt
godel_jupyter.egg-info/dependency_links.txt
godel_jupyter.egg-info/requires.txt
godel_jupyter.egg-info/top_level.txt