Metadata-Version: 2.1
Name: godel-jupyter
Version: 0.0.4
Summary: A Jupyter kernel for Godel.
Maintainer: ZHENG Xunjin
Maintainer-email: zhengxunjin.zx@antgroup.com
Platform: Any
Requires: metakernel (>=0.30.1)
Requires: jupyter_client (>=4.3.0)
Requires: ipykernel
Requires: pandas
License-File: LICENSE
Requires-Dist: metakernel>=0.30.1
Requires-Dist: jupyter_client>=4.3.0
Requires-Dist: ipykernel
Requires-Dist: pandas
